setup.py
chargpt_lfanke/__init__.py
chargpt_lfanke.egg-info/PKG-INFO
chargpt_lfanke.egg-info/SOURCES.txt
chargpt_lfanke.egg-info/dependency_links.txt
chargpt_lfanke.egg-info/top_level.txt